README.md
setup.py
ridi/secret_keeper/__init__.py
ridi_secret_keeper.egg-info/PKG-INFO
ridi_secret_keeper.egg-info/SOURCES.txt
ridi_secret_keeper.egg-info/dependency_links.txt
ridi_secret_keeper.egg-info/requires.txt
ridi_secret_keeper.egg-info/top_level.txt