Metadata-Version: 1.1
Name: ridi-secret-keeper
Version: 0.1.1
Summary: Ridi Secret Keeper
Home-page: https://github.com/ridi/secret-keeper
Author: UNKNOWN
Author-email: UNKNOWN
License: UNKNOWN
Keywords: secret,secret-keeper,ridi,ridibooks
Platform: UNKNOWN
Classifier: License :: OSI Approved :: MIT License
Classifier: Programming Language :: Python :: 3
